src/__init__.py
src/async_funcs.py
src/sync_funcs.py
tasfers/Encrypt.py
tasfers/__init__.py
tasfers/async_funcs.py
tasfers/sync_funcs.py
Tasfers-1.0.6.dist-info/METADATA
Tasfers-1.0.6.dist-info/WHEEL
Tasfers-1.0.6.dist-info/top_level.txt
Tasfers-1.0.6.dist-info/RECORD
