Metadata-Version: 2.1
Name: Tasfers
Version: 1.0.6
Summary: A library to simplify programming
Home-page: https://github.com/Tasfers/library
Author: Towa
License: UNKNOWN
Platform: UNKNOWN
Requires-Dist: aiofiles
Requires-Dist: cryptography ==42.0.4
